Workbook

Sheet Assumptions
A1: CHORELESS — Financial Model Assumptions
A2: Blue cells are inputs — edit them and the model recalculates. All figures are user-provided planning estimates, not market data.
A4: SUBSCRIBERS
A5: Starting subscribers (month 1) | B5: 200 | C5: Launch cohort
A6: Monthly new-subscriber growth rate | B6: 0.15 | C6: New subs each month as % of prior base
A7: Monthly churn rate | B7: 0.05 | C7: Subscribers lost each month
A8: CAC per new subscriber ($) | B8: 80 | C8: Blended paid + referral
A9: TIER MIX & PRICING
A10: Starter share of base | B10: 0.5 | C10: Tier mix assumed constant
A11: Pro share of base | B11: 0.35
A12: Business share of base | B12: 0.15
A13: Starter price ($/mo) | B13: 29 | C13: Matches published pricing
A14: Pro price ($/mo) | B14: 79
A15: Business price ($/mo) | B15: 199
A16: Starter credits / month | B16: 10
A17: Pro credits / month | B17: 30
A18: Business credits / month | B18: 100
A19: Credit utilization | B19: 0.7 | C19: Share of granted credits actually consumed
A20: Fulfillment cost per credit used ($) | B20: 0.55 | C20: Model + tool + QA compute per delivered credit
A21: CHORELESS ADS (premium)
A22: Ads attach rate (% of subscribers) | B22: 0.03 | C22: Subscribers who also buy a managed-ads plan
A23: Average Ads plan ($/mo) | B23: 1100 | C23: Blend of $499 / $1,249 / $2,999 tiers
A24: Ads fulfillment cost (% of ads revenue) | B24: 0.35 | C24: Includes human strategist review
A25: FIXED & VARIABLE OPEX
A26: Base opex ($/mo) | B26: 40000 | C26: Payroll, infra, tools
A27: Variable ops per subscriber ($/mo) | B27: 6 | C27: Support + exception-queue staffing

Sheet Model
A1: CHORELESS — 24-Month Operating Model
A2: All cells below are formulas driven by the Assumptions tab.
A3: Month | B3: 1 | C3: 2 | D3: 3 | E3: 4 | F3: 5 | G3: 6 | H3: 7 | I3: 8 | J3: 9 | K3: 10 | L3: 11 | M3: 12 | N3: 13 | O3: 14 | P3: 15 | Q3: 16 | R3: 17 | S3: 18 | T3: 19 | U3: 20 | V3: 21 | W3: 22 | X3: 23 | Y3: 24
A4: Total subscribers | B4: =Assumptions!$B$5 -> 200 | C4: =B4*(1+Assumptions!$B$6-Assumptions!$B$7) -> 220 | D4: =C4*(1+Assumptions!$B$6-Assumptions!$B$7) -> 242 | E4: =D4*(1+Assumptions!$B$6-Assumptions!$B$7) -> 266.2 | F4: =E4*(1+Assumptions!$B$6-Assumptions!$B$7) -> 292.82 | G4: =F4*(1+Assumptions!$B$6-Assumptions!$B$7) -> 322.102 | H4: =G4*(1+Assumptions!$B$6-Assumptions!$B$7) -> 354.3122 | I4: =H4*(1+Assumptions!$B$6-Assumptions!$B$7) -> 389.74342 | J4: =I4*(1+Assumptions!$B$6-Assumptions!$B$7) -> 428.71776 | ... Y4: =X4*(1+Assumptions!$B$6-Assumptions!$B$7) -> 1790.8605
A5: New subscribers | B5: =B4 -> 200 | C5: =B4*Assumptions!$B$6 -> 30 | D5: =C4*Assumptions!$B$6 -> 33 | E5: =D4*Assumptions!$B$6 -> 36.3 | F5: =E4*Assumptions!$B$6 -> 39.93 | G5: =F4*Assumptions!$B$6 -> 43.923 | H5: =G4*Assumptions!$B$6 -> 48.3153 | I5: =H4*Assumptions!$B$6 -> 53.14683 | J5: =I4*Assumptions!$B$6 -> 58.461513 | ... Y5: =X4*Assumptions!$B$6 -> 244.20825
A6: Starter subscribers | B6: =B4*Assumptions!$B$10 -> 100 | C6: =C4*Assumptions!$B$10 -> 110 | D6: =D4*Assumptions!$B$10 -> 121 | E6: =E4*Assumptions!$B$10 -> 133.1 | F6: =F4*Assumptions!$B$10 -> 146.41 | G6: =G4*Assumptions!$B$10 -> 161.051 | H6: =H4*Assumptions!$B$10 -> 177.1561 | I6: =I4*Assumptions!$B$10 -> 194.87171 | ... Y6: =Y4*Assumptions!$B$10 -> 895.43024
A7: Pro subscribers | B7: =B4*Assumptions!$B$11 -> 70 | C7: =C4*Assumptions!$B$11 -> 77 | D7: =D4*Assumptions!$B$11 -> 84.7 | E7: =E4*Assumptions!$B$11 -> 93.17 | F7: =F4*Assumptions!$B$11 -> 102.487 | G7: =G4*Assumptions!$B$11 -> 112.7357 | H7: =H4*Assumptions!$B$11 -> 124.00927 | I7: =I4*Assumptions!$B$11 -> 136.4102 | ... Y7: =Y4*Assumptions!$B$11 -> 626.80117
A8: Business subscribers | B8: =B4*Assumptions!$B$12 -> 30 | C8: =C4*Assumptions!$B$12 -> 33 | D8: =D4*Assumptions!$B$12 -> 36.3 | E8: =E4*Assumptions!$B$12 -> 39.93 | F8: =F4*Assumptions!$B$12 -> 43.923 | G8: =G4*Assumptions!$B$12 -> 48.3153 | H8: =H4*Assumptions!$B$12 -> 53.14683 | I8: =I4*Assumptions!$B$12 -> 58.461513 | ... Y8: =Y4*Assumptions!$B$12 -> 268.62907
A10: Starter revenue | B10: =B6*Assumptions!$B$13 -> 2900 | C10: =C6*Assumptions!$B$13 -> 3190 | D10: =D6*Assumptions!$B$13 -> 3509 | E10: =E6*Assumptions!$B$13 -> 3859.9 | F10: =F6*Assumptions!$B$13 -> 4245.89 | G10: =G6*Assumptions!$B$13 -> 4670.479 | H10: =H6*Assumptions!$B$13 -> 5137.5269 | I10: =I6*Assumptions!$B$13 -> 5651.2796 | ... Y10: =Y6*Assumptions!$B$13 -> 25967.477
A11: Pro revenue | B11: =B7*Assumptions!$B$14 -> 5530 | C11: =C7*Assumptions!$B$14 -> 6083 | D11: =D7*Assumptions!$B$14 -> 6691.3 | E11: =E7*Assumptions!$B$14 -> 7360.43 | F11: =F7*Assumptions!$B$14 -> 8096.473 | G11: =G7*Assumptions!$B$14 -> 8906.1203 | H11: =H7*Assumptions!$B$14 -> 9796.7323 | I11: =I7*Assumptions!$B$14 -> 10776.406 | ... Y11: =Y7*Assumptions!$B$14 -> 49517.292
A12: Business revenue | B12: =B8*Assumptions!$B$15 -> 5970 | C12: =C8*Assumptions!$B$15 -> 6567 | D12: =D8*Assumptions!$B$15 -> 7223.7 | E12: =E8*Assumptions!$B$15 -> 7946.07 | F12: =F8*Assumptions!$B$15 -> 8740.677 | G12: =G8*Assumptions!$B$15 -> 9614.7447 | H12: =H8*Assumptions!$B$15 -> 10576.219 | I12: =I8*Assumptions!$B$15 -> 11633.841 | ... Y12: =Y8*Assumptions!$B$15 -> 53457.186
A13: Subscription MRR | B13: =SUM(B10:B12) -> 14400 | C13: =SUM(C10:C12) -> 15840 | D13: =SUM(D10:D12) -> 17424 | E13: =SUM(E10:E12) -> 19166.4 | F13: =SUM(F10:F12) -> 21083.04 | G13: =SUM(G10:G12) -> 23191.344 | H13: =SUM(H10:H12) -> 25510.478 | I13: =SUM(I10:I12) -> 28061.526 | ... Y13: =SUM(Y10:Y12) -> 128941.96
A14: Ads customers | B14: =B4*Assumptions!$B$22 -> 6 | C14: =C4*Assumptions!$B$22 -> 6.6 | D14: =D4*Assumptions!$B$22 -> 7.26 | E14: =E4*Assumptions!$B$22 -> 7.986 | F14: =F4*Assumptions!$B$22 -> 8.7846 | G14: =G4*Assumptions!$B$22 -> 9.66306 | H14: =H4*Assumptions!$B$22 -> 10.629366 | I14: =I4*Assumptions!$B$22 -> 11.692303 | ... Y14: =Y4*Assumptions!$B$22 -> 53.725815
A15: Ads revenue | B15: =B14*Assumptions!$B$23 -> 6600 | C15: =C14*Assumptions!$B$23 -> 7260 | D15: =D14*Assumptions!$B$23 -> 7986 | E15: =E14*Assumptions!$B$23 -> 8784.6 | F15: =F14*Assumptions!$B$23 -> 9663.06 | G15: =G14*Assumptions!$B$23 -> 10629.366 | H15: =H14*Assumptions!$B$23 -> 11692.303 | I15: =I14*Assumptions!$B$23 -> 12861.533 | ... Y15: =Y14*Assumptions!$B$23 -> 59098.396
A16: TOTAL REVENUE | B16: =B13+B15 -> 21000 | C16: =C13+C15 -> 23100 | D16: =D13+D15 -> 25410 | E16: =E13+E15 -> 27951 | F16: =F13+F15 -> 30746.1 | G16: =G13+G15 -> 33820.71 | H16: =H13+H15 -> 37202.781 | I16: =I13+I15 -> 40923.059 | ... Y16: =Y13+Y15 -> 188040.35
A18: Credits used | B18: =(B6*Assumptions!$B$16+B7*Assumptions!$B$17+B8*Assumptions!$B$18)*Assumptions!$B$19 -> 4270 | C18: =(C6*Assumptions!$B$16+C7*Assumptions!$B$17+C8*Assumptions!$B$18)*Assumptions!$B$19 -> 4697 | D18: =(D6*Assumptions!$B$16+D7*Assumptions!$B$17+D8*Assumptions!$B$18)*Assumptions!$B$19 -> 5166.7 | E18: =(E6*Assumptions!$B$16+E7*Assumptions!$B$17+E8*Assumptions!$B$18)*Assumptions!$B$19 -> 5683.37 | F18: =(F6*Assumptions!$B$16+F7*Assumptions!$B$17+F8*Assumptions!$B$18)*Assumptions!$B$19 -> 6251.707 | G18: =(G6*Assumptions!$B$16+G7*Assumptions!$B$17+G8*Assumptions!$B$18)*Assumptions!$B$19 -> 6876.8777 | H18: =(H6*Assumptions!$B$16+H7*Assumptions!$B$17+H8*Assumptions!$B$18)*Assumptions!$B$19 -> 7564.5655 | I18: =(I6*Assumptions!$B$16+I7*Assumptions!$B$17+I8*Assumptions!$B$18)*Assumptions!$B$19 -> 8321.022 | ... Y18: =(Y6*Assumptions!$B$16+Y7*Assumptions!$B$17+Y8*Assumptions!$B$18)*Assumptions!$B$19 -> 38234.871
A19: Subscription fulfillment cost | B19: =B18*Assumptions!$B$20 -> 2348.5 | C19: =C18*Assumptions!$B$20 -> 2583.35 | D19: =D18*Assumptions!$B$20 -> 2841.685 | E19: =E18*Assumptions!$B$20 -> 3125.8535 | F19: =F18*Assumptions!$B$20 -> 3438.4389 | G19: =G18*Assumptions!$B$20 -> 3782.2827 | H19: =H18*Assumptions!$B$20 -> 4160.511 | I19: =I18*Assumptions!$B$20 -> 4576.5621 | ... Y19: =Y18*Assumptions!$B$20 -> 21029.179
A20: Ads fulfillment cost | B20: =B15*Assumptions!$B$24 -> 2310 | C20: =C15*Assumptions!$B$24 -> 2541 | D20: =D15*Assumptions!$B$24 -> 2795.1 | E20: =E15*Assumptions!$B$24 -> 3074.61 | F20: =F15*Assumptions!$B$24 -> 3382.071 | G20: =G15*Assumptions!$B$24 -> 3720.2781 | H20: =H15*Assumptions!$B$24 -> 4092.3059 | I20: =I15*Assumptions!$B$24 -> 4501.5365 | ... Y20: =Y15*Assumptions!$B$24 -> 20684.439
A21: Marketing (CAC x new subs) | B21: =B5*Assumptions!$B$8 -> 16000 | C21: =C5*Assumptions!$B$8 -> 2400 | D21: =D5*Assumptions!$B$8 -> 2640 | E21: =E5*Assumptions!$B$8 -> 2904 | F21: =F5*Assumptions!$B$8 -> 3194.4 | G21: =G5*Assumptions!$B$8 -> 3513.84 | H21: =H5*Assumptions!$B$8 -> 3865.224 | I21: =I5*Assumptions!$B$8 -> 4251.7464 | ... Y21: =Y5*Assumptions!$B$8 -> 19536.66
A22: Opex (base + variable) | B22: =Assumptions!$B$26+B4*Assumptions!$B$27 -> 41200 | C22: =Assumptions!$B$26+C4*Assumptions!$B$27 -> 41320 | D22: =Assumptions!$B$26+D4*Assumptions!$B$27 -> 41452 | E22: =Assumptions!$B$26+E4*Assumptions!$B$27 -> 41597.2 | F22: =Assumptions!$B$26+F4*Assumptions!$B$27 -> 41756.92 | G22: =Assumptions!$B$26+G4*Assumptions!$B$27 -> 41932.612 | H22: =Assumptions!$B$26+H4*Assumptions!$B$27 -> 42125.873 | I22: =Assumptions!$B$26+I4*Assumptions!$B$27 -> 42338.461 | ... Y22: =Assumptions!$B$26+Y4*Assumptions!$B$27 -> 50745.163
A23: TOTAL COSTS | B23: =SUM(B19:B22) -> 61858.5 | C23: =SUM(C19:C22) -> 48844.35 | D23: =SUM(D19:D22) -> 49728.785 | E23: =SUM(E19:E22) -> 50701.664 | F23: =SUM(F19:F22) -> 51771.83 | G23: =SUM(G19:G22) -> 52949.013 | H23: =SUM(H19:H22) -> 54243.914 | I23: =SUM(I19:I22) -> 55668.306 | ... Y23: =SUM(Y19:Y22) -> 111995.44
A25: EBITDA | B25: =B16-B23 -> -40858.5 | C25: =C16-C23 -> -25744.35 | D25: =D16-D23 -> -24318.785 | E25: =E16-E23 -> -22750.663 | F25: =F16-F23 -> -21025.73 | G25: =G16-G23 -> -19128.303 | H25: =H16-H23 -> -17041.133 | I25: =I16-I23 -> -14745.246 | ... Y25: =Y16-Y23 -> 76044.91
A26: Cumulative EBITDA | B26: =B25 -> -40858.5 | C26: =B26+C25 -> -66602.85 | D26: =C26+D25 -> -90921.635 | E26: =D26+E25 -> -113672.3 | F26: =E26+F25 -> -134698.03 | G26: =F26+G25 -> -153826.33 | H26: =G26+H25 -> -170867.46 | I26: =H26+I25 -> -185612.71 | J26: =I26+J25 -> -197832.48 | ... Y26: =X26+Y25 -> 173079.01
A27: Gross margin % | B27: =IF(B16=0,0,(B16-B19-B20)/B16) -> 0.77816667 | C27: =IF(C16=0,0,(C16-C19-C20)/C16) -> 0.77816667 | D27: =IF(D16=0,0,(D16-D19-D20)/D16) -> 0.77816667 | E27: =IF(E16=0,0,(E16-E19-E20)/E16) -> 0.77816667 | F27: =IF(F16=0,0,(F16-F19-F20)/F16) -> 0.77816667 | G27: =IF(G16=0,0,(G16-G19-G20)/G16) -> 0.77816667 | H27: =IF(H16=0,0,(H16-H19-H20)/H16) -> 0.77816667 | I27: =IF(I16=0,0,(I16-I19-I20)/I16) -> 0.77816667 | ... Y27: =IF(Y16=0,0,(Y16-Y19-Y20)/Y16) -> 0.77816667

Sheet Summary
A1: CHORELESS — Summary
B3: Month 12 | C3: Month 24
A4: Subscribers | B4: =Model!M4 -> 570.62334 | C4: =Model!Y4 -> 1790.8605
A5: Subscription MRR | B5: =Model!M13 -> 41084.881 | C5: =Model!Y13 -> 128941.96
A6: Ads revenue / month | B6: =Model!M15 -> 18830.57 | C6: =Model!Y15 -> 59098.396
A7: Total revenue / month | B7: =Model!M16 -> 59915.451 | C7: =Model!Y16 -> 188040.35
A8: Annual run-rate (ARR) | B8: =Model!M16*12 -> 718985.41 | C8: =Model!Y16*12 -> 2256484.2
A9: Gross margin % | B9: =Model!M27 -> 0.77816667 | C9: =Model!Y27 -> 0.77816667
A10: EBITDA / month | B10: =Model!M25 -> -3024.5153 | C10: =Model!Y25 -> 76044.91
A11: Cumulative EBITDA | B11: =Model!M26 -> -216684.67 | C11: =Model!Y26 -> 173079.01
A13: Break-even month (first month EBITDA > 0) | B13: =COUNTIF(Model!B25:Y25,"<0")+1 -> 13 | C13: If 25, not reached within 24 months
A15: Unit economics
A16: Blended ARPU ($/mo) | B16: =Assumptions!B10*Assumptions!B13+Assumptions!B11*Assumptions!B14+Assumptions!B12*Assumptions!B15 -> 72
A17: Avg customer lifetime (months, 1/churn) | B17: =1/Assumptions!B7 -> 20
A18: LTV (ARPU x lifetime x gross margin M12) | B18: =B16*B17*Model!M27 -> 1120.56
A19: LTV : CAC | B19: =B18/Assumptions!B8 -> 14.007
A21: Legend: blue = editable input (Assumptions tab) · black = formula · green = pulls from another sheet.
